nova_adminclient
