Metadata-Version: 1.0
Name: nova-adminclient
Version: 0.1.8
Summary: client for administering OpenStack Nova
Home-page: http://www.openstack.org
Author: OpenStack
Author-email: nova@lists.launchpad.net
License: Apache License (2.0)
Platform: UNKNOWN
Classifier: Development Status :: 5 - Production/Stable
Classifier: Intended Audience :: Developers
Classifier: License :: OSI Approved :: Apache Software License
Classifier: Operating System :: OS Independent
Classifier: Programming Language :: Python :: 2.6
Classifier: Topic :: Internet :: WWW/HTTP
